{
  "timestamp": "2026-05-25T08:11:05.575Z",
  "source": "Masaki Trade System",
  "scan": {
    "status": "idle_or_not_started",
    "current": 0,
    "total": 0,
    "success": 0,
    "pending": 0,
    "active": false,
    "complete": false,
    "stage": "準備中",
    "focusUpdated": "2026/5/25 17:11:05",
    "watchUpdated": "2026/5/25 17:03:14"
  },
  "focus": [
    {
      "rank": 1,
      "code": "3694",
      "name": "オプティム",
      "signal": "ENTRY",
      "entryStatus": "ENTRY",
      "trend": "LONG",
      "theme": "AI / 農業DX / クラウド",
      "score": 80,
      "initialScore": 55,
      "volumeRatio": "",
      "priceChange": "",
      "entry": "401.8-404.3",
      "sl": "393.8",
      "tp": "424.5",
      "risk": "入り候補",
      "comment": "資金流入"
    },
    {
      "rank": 2,
      "code": "1397",
      "name": "SMDAM 日経225上場投信",
      "signal": "WAIT",
      "entryStatus": "WAIT",
      "trend": "LONG",
      "theme": "ETF / 日経平均 / 日本株",
      "score": 80,
      "initialScore": 15,
      "volumeRatio": "",
      "priceChange": "",
      "entry": "39004.6-39239.4",
      "sl": "38224.5",
      "tp": "41201.3",
      "risk": "利確警戒",
      "comment": "そろそろ初動か？"
    },
    {
      "rank": 3,
      "code": "2802",
      "name": "味の素",
      "signal": "WAIT",
      "entryStatus": "WAIT",
      "trend": "WATCH",
      "theme": "食品 / ディフェンシブ",
      "score": 60,
      "initialScore": 0,
      "volumeRatio": "",
      "priceChange": "",
      "entry": "",
      "sl": "",
      "tp": "",
      "risk": "利確警戒",
      "comment": "そろそろ初動か？"
    },
    {
      "rank": 4,
      "code": "5351",
      "name": "品川リフラクトリーズ",
      "signal": "WAIT",
      "entryStatus": "WAIT",
      "trend": "WATCH",
      "theme": "耐火物 / インフラ / 製鉄",
      "score": 60,
      "initialScore": 0,
      "volumeRatio": "",
      "priceChange": "",
      "entry": "",
      "sl": "",
      "tp": "",
      "risk": "利確警戒",
      "comment": "監視継続"
    },
    {
      "rank": 5,
      "code": "9416",
      "name": "ビジョン",
      "signal": "WAIT",
      "entryStatus": "WAIT",
      "trend": "WATCH",
      "theme": "通信 / 旅行 / DX",
      "score": 60,
      "initialScore": 0,
      "volumeRatio": "",
      "priceChange": "",
      "entry": "",
      "sl": "",
      "tp": "",
      "risk": "利確警戒",
      "comment": "そろそろ初動か？"
    },
    {
      "rank": 6,
      "code": "8591",
      "name": "オリックス",
      "signal": "WAIT",
      "entryStatus": "WAIT",
      "trend": "WATCH",
      "theme": "リース / 金融 / 再エネ",
      "score": 30,
      "initialScore": 0,
      "volumeRatio": "",
      "priceChange": "",
      "entry": "",
      "sl": "",
      "tp": "",
      "risk": "利確警戒",
      "comment": "ブレイク待ち"
    }
  ],
  "watch": [
    {
      "rank": 1,
      "code": "6724",
      "name": "セイコーエプソン",
      "signal": "UP",
      "theme": "プリンター / FA / 省力化",
      "score": 100,
      "volumeRatio": "",
      "priceChange": "",
      "reason": "増加"
    },
    {
      "rank": 2,
      "code": "9502",
      "name": "中部電力",
      "signal": "UP",
      "theme": "原子力 / 電力 / インフラ",
      "score": 100,
      "volumeRatio": "",
      "priceChange": "",
      "reason": "増加"
    },
    {
      "rank": 3,
      "code": "6627",
      "name": "テラプローブ",
      "signal": "UP",
      "theme": "半導体検査 / 後工程 / AI",
      "score": 100,
      "volumeRatio": "",
      "priceChange": "",
      "reason": "増加"
    },
    {
      "rank": 4,
      "code": "7911",
      "name": "TOPPAN HD",
      "signal": "UP",
      "theme": "印刷 / 半導体パッケージ / DX",
      "score": 100,
      "volumeRatio": "",
      "priceChange": "",
      "reason": "増加"
    },
    {
      "rank": 5,
      "code": "6961",
      "name": "エンプラス",
      "signal": "UP",
      "theme": "半導体 / ICソケット / 電子部品",
      "score": 80,
      "volumeRatio": "",
      "priceChange": "",
      "reason": "通常"
    },
    {
      "rank": 6,
      "code": "7780",
      "name": "メニコン",
      "signal": "UP",
      "theme": "コンタクトレンズ / 医療機器 / ヘルスケア",
      "score": 80,
      "volumeRatio": "",
      "priceChange": "",
      "reason": "通常"
    },
    {
      "rank": 7,
      "code": "7013",
      "name": "IHI",
      "signal": "UP",
      "theme": "防衛",
      "score": 80,
      "volumeRatio": "",
      "priceChange": "",
      "reason": "通常"
    },
    {
      "rank": 8,
      "code": "7984",
      "name": "コクヨ",
      "signal": "UP",
      "theme": "事務用品 / オフィス / 教育ICT",
      "score": 80,
      "volumeRatio": "",
      "priceChange": "",
      "reason": "通常"
    },
    {
      "rank": 9,
      "code": "6432",
      "name": "竹内製作所",
      "signal": "UP",
      "theme": "建機 / 北米住宅 / インフラ",
      "score": 80,
      "volumeRatio": "",
      "priceChange": "",
      "reason": "通常"
    },
    {
      "rank": 10,
      "code": "3405",
      "name": "クラレ",
      "signal": "UP",
      "theme": "化学 / 高機能素材 / 樹脂",
      "score": 80,
      "volumeRatio": "",
      "priceChange": "",
      "reason": "通常"
    },
    {
      "rank": 11,
      "code": "4704",
      "name": "トレンドマイクロ",
      "signal": "UP",
      "theme": "サイバーセキュリティ / ソフトウェア / DX",
      "score": 80,
      "volumeRatio": "",
      "priceChange": "",
      "reason": "通常"
    },
    {
      "rank": 12,
      "code": "4475",
      "name": "HENNGE",
      "signal": "UP",
      "theme": "クラウドセキュリティ / SaaS / DX",
      "score": 80,
      "volumeRatio": "",
      "priceChange": "",
      "reason": "通常"
    },
    {
      "rank": 13,
      "code": "9735",
      "name": "セコム",
      "signal": "UP",
      "theme": "DX",
      "score": 80,
      "volumeRatio": "",
      "priceChange": "",
      "reason": "通常"
    },
    {
      "rank": 14,
      "code": "4631",
      "name": "DIC",
      "signal": "UP",
      "theme": "化学 / 印刷材料 / 電子材料",
      "score": 80,
      "volumeRatio": "",
      "priceChange": "",
      "reason": "通常"
    },
    {
      "rank": 15,
      "code": "8804",
      "name": "東京建物",
      "signal": "UP",
      "theme": "不動産 / 再開発 / オフィス",
      "score": 80,
      "volumeRatio": "",
      "priceChange": "",
      "reason": "通常"
    }
  ]
}
