{
  "timestamp": "2026-06-10T06:54:52.278Z",
  "source": "Masaki Trade System",
  "scan": {
    "status": "complete",
    "current": 33,
    "total": 33,
    "success": 33,
    "pending": 0,
    "active": false,
    "complete": true,
    "stage": "通知前再評価完了",
    "focusUpdated": "2026/6/10 15:54:52",
    "watchUpdated": "2026/6/10 15:54:52"
  },
  "focus": [
    {
      "rank": 1,
      "code": "3661",
      "name": "エムアップHD",
      "signal": "WAIT",
      "entryStatus": "WAIT",
      "trend": "LONG",
      "theme": "エンタメ / ファンクラブ / DX",
      "score": 80,
      "initialScore": 82,
      "volumeRatio": "",
      "priceChange": "",
      "entry": "672.2-676.3",
      "sl": "658.8",
      "tp": "710.1",
      "risk": "ブレイク待ち",
      "comment": "監視継続",
      "focusTier": "PREPARATION",
      "focusLabel": "継続監視",
      "hourly": {
        "available": true,
        "score": 75,
        "grade": "B",
        "pass": true,
        "entryAllowed": true,
        "hardFail": false,
        "pattern": "higher_low_breakout_setup",
        "overheadRoomPct": 1.7777777777777777,
        "higherHigh": true,
        "higherLow": true,
        "reasons": [
          "price_above_ema9",
          "price_above_ema21",
          "ema9_above_ema21",
          "ema9_up",
          "ema21_up",
          "higher_low",
          "higher_high",
          "near_ema_rebound_area",
          "contracting_near_high",
          "pullback_volume_cooling"
        ],
        "risks": [],
        "ema9": 668.7875143723895,
        "ema21": 662.7259902190573
      },
      "fibonacci": {
        "available": true,
        "impulseLow": 600,
        "impulseHigh": 672,
        "impulsePct": 12,
        "pullbackLow": 657,
        "pullbackRatio": 0.20833333333333334,
        "reboundRatio": 1.2,
        "state": "shallow_pullback",
        "retracementZone": "<23.6",
        "target382": 662.73,
        "target500": 664.5,
        "target618": 666.27,
        "previousHigh": 672
      }
    },
    {
      "rank": 2,
      "code": "9602",
      "name": "東宝",
      "signal": "WAIT",
      "entryStatus": "WAIT",
      "trend": "LONG",
      "theme": "映画 / エンタメ / IP",
      "score": 80,
      "initialScore": 82,
      "volumeRatio": "",
      "priceChange": "",
      "entry": "1314.0-1321.9",
      "sl": "1287.8",
      "tp": "1388.0",
      "risk": "ブレイク待ち",
      "comment": "資金入り始め",
      "focusTier": "PREPARATION",
      "focusLabel": "ブレイク待ち",
      "hourly": {
        "available": true,
        "score": 71,
        "grade": "B",
        "pass": true,
        "entryAllowed": true,
        "hardFail": false,
        "pattern": "higher_low_breakout_setup",
        "overheadRoomPct": -0.07584376185058779,
        "higherHigh": true,
        "higherLow": true,
        "reasons": [
          "price_above_ema9",
          "price_above_ema21",
          "ema9_above_ema21",
          "ema9_up",
          "ema21_up",
          "higher_low",
          "higher_high",
          "near_ema_rebound_area",
          "contracting_near_high",
          "breakout_area"
        ],
        "risks": [],
        "ema9": 1305.2440729355721,
        "ema21": 1286.6711212030461
      },
      "fibonacci": {
        "available": true,
        "impulseLow": 1197,
        "impulseHigh": 1318.5,
        "impulsePct": 10.150375939849624,
        "pullbackLow": 1318.5,
        "pullbackRatio": 0,
        "reboundRatio": 0,
        "state": "shallow_pullback",
        "retracementZone": "<23.6",
        "target382": 1318.5,
        "target500": 1318.5,
        "target618": 1318.5,
        "previousHigh": 1318.5
      }
    }
  ],
  "watch": [
    {
      "rank": 1,
      "code": "4543",
      "name": "テルモ",
      "signal": "UP",
      "theme": "医療機器 / ヘルスケア / ディフェンシブ",
      "score": 80,
      "volumeRatio": "",
      "priceChange": "",
      "reason": "通常",
      "hourly": {
        "available": true,
        "score": 69,
        "grade": "C",
        "pass": false,
        "entryAllowed": false,
        "hardFail": false,
        "pattern": "higher_low_breakout_setup",
        "overheadRoomPct": -0.0649772579597141,
        "higherHigh": true,
        "higherLow": true,
        "reasons": [
          "price_above_ema9",
          "price_above_ema21",
          "ema9_above_ema21",
          "ema9_up",
          "ema21_up",
          "higher_low",
          "higher_high",
          "near_ema_rebound_area",
          "contracting_near_high",
          "volume_rising",
          "breakout_area"
        ],
        "risks": [
          "upper_wicks"
        ],
        "ema9": 2291.4443917375784,
        "ema21": 2287.2192592011083
      },
      "fibonacci": {
        "available": false,
        "impulsePct": 0,
        "pullbackRatio": 0,
        "reboundRatio": 0,
        "state": "unavailable",
        "retracementZone": "",
        "target382": 0,
        "target500": 0,
        "target618": 0,
        "previousHigh": 0
      }
    },
    {
      "rank": 2,
      "code": "7810",
      "name": "クロスフォー",
      "signal": "WATCH",
      "theme": "ダイヤモンド / 宝飾品 / EC",
      "score": 61,
      "volumeRatio": "",
      "priceChange": "",
      "reason": "1H監視",
      "hourly": {
        "available": true,
        "score": 61,
        "grade": "C",
        "pass": false,
        "entryAllowed": false,
        "hardFail": false,
        "pattern": "range_watch",
        "overheadRoomPct": 0,
        "higherHigh": false,
        "higherLow": true,
        "reasons": [
          "price_above_ema9",
          "price_above_ema21",
          "ema9_above_ema21",
          "ema9_up",
          "ema21_up",
          "higher_low",
          "near_ema_rebound_area",
          "contracting_near_high",
          "breakout_area",
          "pullback_volume_cooling"
        ],
        "risks": [
          "upper_wicks"
        ],
        "ema9": 170.7947317890207,
        "ema21": 169.81852674499504
      },
      "fibonacci": {
        "available": false,
        "impulsePct": 0,
        "pullbackRatio": 0,
        "reboundRatio": 0,
        "state": "unavailable",
        "retracementZone": "",
        "target382": 0,
        "target500": 0,
        "target618": 0,
        "previousHigh": 0
      }
    },
    {
      "rank": 3,
      "code": "2413",
      "name": "エムスリー",
      "signal": "UP",
      "theme": "医療DX / ヘルスケア / ネットサービス",
      "score": 80,
      "volumeRatio": "",
      "priceChange": "",
      "reason": "1H監視",
      "hourly": {
        "available": true,
        "score": 59,
        "grade": "D",
        "pass": false,
        "entryAllowed": false,
        "hardFail": false,
        "pattern": "higher_low_breakout_setup",
        "overheadRoomPct": 0.938824954572986,
        "higherHigh": true,
        "higherLow": true,
        "reasons": [
          "price_above_ema9",
          "price_above_ema21",
          "ema9_above_ema21",
          "ema9_up",
          "ema21_up",
          "higher_low",
          "higher_high",
          "near_ema_rebound_area",
          "contracting_near_high",
          "pullback_volume_cooling"
        ],
        "risks": [
          "low_overhead_room",
          "upper_wicks"
        ],
        "ema9": 1640.8145337870506,
        "ema21": 1626.530341614045
      },
      "fibonacci": {
        "available": true,
        "impulseLow": 1365.5,
        "impulseHigh": 1561,
        "impulsePct": 14.317099963383376,
        "pullbackLow": 1509,
        "pullbackRatio": 0.2659846547314578,
        "reboundRatio": 2.730769230769231,
        "state": "strong_shallow_pullback",
        "retracementZone": "23.6-38.2",
        "target382": 1528.864,
        "target500": 1535,
        "target618": 1541.136,
        "previousHigh": 1561
      }
    },
    {
      "rank": 4,
      "code": "9008",
      "name": "京王電鉄",
      "signal": "WATCH",
      "theme": "鉄道 / 不動産 / 内需",
      "score": 80,
      "volumeRatio": "",
      "priceChange": "",
      "reason": "1H監視",
      "hourly": {
        "available": true,
        "score": 59,
        "grade": "D",
        "pass": false,
        "entryAllowed": false,
        "hardFail": false,
        "pattern": "range_watch",
        "overheadRoomPct": -0.13164824014490306,
        "higherHigh": false,
        "higherLow": true,
        "reasons": [
          "price_above_ema9",
          "price_above_ema21",
          "ema9_above_ema21",
          "ema9_up",
          "ema21_up",
          "higher_low",
          "near_ema_rebound_area",
          "contracting_near_high",
          "volume_rising",
          "breakout_area"
        ],
        "risks": [
          "lower_high"
        ],
        "ema9": 751.4700218219361,
        "ema21": 744.2696617385734
      },
      "fibonacci": {
        "available": false,
        "impulsePct": 0,
        "pullbackRatio": 0,
        "reboundRatio": 0,
        "state": "unavailable",
        "retracementZone": "",
        "target382": 0,
        "target500": 0,
        "target618": 0,
        "previousHigh": 0
      }
    },
    {
      "rank": 5,
      "code": "9735",
      "name": "セコム",
      "signal": "WATCH",
      "theme": "DX",
      "score": 80,
      "volumeRatio": "",
      "priceChange": "",
      "reason": "1H監視",
      "hourly": {
        "available": true,
        "score": 57,
        "grade": "D",
        "pass": false,
        "entryAllowed": false,
        "hardFail": false,
        "pattern": "range_watch",
        "overheadRoomPct": 0,
        "higherHigh": false,
        "higherLow": true,
        "reasons": [
          "price_above_ema9",
          "price_above_ema21",
          "ema9_above_ema21",
          "ema9_up",
          "ema21_up",
          "higher_low",
          "near_ema_rebound_area",
          "contracting_near_high",
          "breakout_area"
        ],
        "risks": [
          "lower_high"
        ],
        "ema9": 6508.365414900468,
        "ema21": 6464.061915482204
      },
      "fibonacci": {
        "available": false,
        "impulsePct": 0,
        "pullbackRatio": 0,
        "reboundRatio": 0,
        "state": "unavailable",
        "retracementZone": "",
        "target382": 0,
        "target500": 0,
        "target618": 0,
        "previousHigh": 0
      }
    },
    {
      "rank": 6,
      "code": "4901",
      "name": "富士フイルムHD",
      "signal": "WATCH",
      "theme": "医療機器 / 精密 / ヘルスケア",
      "score": 56,
      "volumeRatio": "",
      "priceChange": "",
      "reason": "1H監視",
      "hourly": {
        "available": true,
        "score": 56,
        "grade": "D",
        "pass": false,
        "entryAllowed": false,
        "hardFail": false,
        "pattern": "higher_low_breakout_setup",
        "overheadRoomPct": 1.4768531667140017,
        "higherHigh": true,
        "higherLow": true,
        "reasons": [
          "price_above_ema9",
          "price_above_ema21",
          "ema9_above_ema21",
          "ema9_up",
          "ema21_up",
          "higher_low",
          "higher_high",
          "near_ema_rebound_area",
          "contracting_near_high"
        ],
        "risks": [
          "low_overhead_room",
          "upper_wicks"
        ],
        "ema9": 3504.819989810234,
        "ema21": 3492.9302703249987
      },
      "fibonacci": {
        "available": true,
        "impulseLow": 3147,
        "impulseHigh": 3407,
        "impulsePct": 8.261836669844296,
        "pullbackLow": 3325,
        "pullbackRatio": 0.3153846153846154,
        "reboundRatio": 2.3902439024390243,
        "state": "strong_shallow_pullback",
        "retracementZone": "23.6-38.2",
        "target382": 3356.324,
        "target500": 3366,
        "target618": 3375.676,
        "previousHigh": 3407
      }
    },
    {
      "rank": 7,
      "code": "3561",
      "name": "力の源ホールディングス",
      "signal": "WATCH",
      "theme": "外食 / ラーメン / 海外展開",
      "score": 56,
      "volumeRatio": "",
      "priceChange": "",
      "reason": "1H監視",
      "hourly": {
        "available": true,
        "score": 56,
        "grade": "D",
        "pass": false,
        "entryAllowed": false,
        "hardFail": false,
        "pattern": "higher_low_breakout_setup",
        "overheadRoomPct": 0.8580858085808581,
        "higherHigh": true,
        "higherLow": true,
        "reasons": [
          "price_above_ema9",
          "price_above_ema21",
          "ema9_above_ema21",
          "ema9_up",
          "ema21_up",
          "higher_low",
          "higher_high",
          "near_ema_rebound_area",
          "contracting_near_high"
        ],
        "risks": [
          "low_overhead_room",
          "upper_wicks"
        ],
        "ema9": 1514.317035027502,
        "ema21": 1502.7769168375164
      },
      "fibonacci": {
        "available": false,
        "impulsePct": 0,
        "pullbackRatio": 0,
        "reboundRatio": 0,
        "state": "unavailable",
        "retracementZone": "",
        "target382": 0,
        "target500": 0,
        "target618": 0,
        "previousHigh": 0
      }
    },
    {
      "rank": 8,
      "code": "9433",
      "name": "KDDI",
      "signal": "WATCH",
      "theme": "AI",
      "score": 80,
      "volumeRatio": "",
      "priceChange": "",
      "reason": "1H監視",
      "hourly": {
        "available": true,
        "score": 54,
        "grade": "D",
        "pass": false,
        "entryAllowed": false,
        "hardFail": false,
        "pattern": "range_watch",
        "overheadRoomPct": -0.05450581395348837,
        "higherHigh": true,
        "higherLow": false,
        "reasons": [
          "price_above_ema9",
          "price_above_ema21",
          "ema9_above_ema21",
          "ema9_up",
          "ema21_up",
          "higher_high",
          "near_ema_rebound_area",
          "contracting_near_high",
          "breakout_area"
        ],
        "risks": [
          "lower_low"
        ],
        "ema9": 2732.6633572233104,
        "ema21": 2718.5540165471384
      },
      "fibonacci": {
        "available": false,
        "impulsePct": 0,
        "pullbackRatio": 0,
        "reboundRatio": 0,
        "state": "unavailable",
        "retracementZone": "",
        "target382": 0,
        "target500": 0,
        "target618": 0,
        "previousHigh": 0
      }
    }
  ],
  "themePatterns": [
    {
      "theme": "ヘルスケア",
      "sampleCount": 3,
      "matchedCount": 2,
      "confidence": 0.67,
      "state": "strong_shallow_pullback",
      "summary": "strong_shallow_pullback"
    }
  ],
  "usdJpyRadar": {
    "bias": "neutral",
    "biasLabel": "中立",
    "yenWeakScore": 0,
    "yenStrongScore": 0,
    "shortPolicy": "ノートレード",
    "summary": "中立。ドル円は方向感確認までノートレード優先。",
    "stockImpact": "為替影響は中立。個別材料と金利・指数を優先確認。",
    "watchEvents": [
      "米CPI",
      "FOMC",
      "雇用統計",
      "PCE",
      "日銀会合",
      "要人発言",
      "為替介入警戒"
    ],
    "yenWeakMaterials": [],
    "yenStrongMaterials": [],
    "updatedAt": "2026/6/10 15:54:52"
  }
}
